docuprox/__init__.py
docuprox/client.py
docuprox-0.1.1.dist-info/licenses/LICENSE
docuprox-0.1.1.dist-info/METADATA
docuprox-0.1.1.dist-info/WHEEL
docuprox-0.1.1.dist-info/top_level.txt
docuprox-0.1.1.dist-info/RECORD
