Metadata-Version: 2.4
Name: docuprox
Version: 0.1.1
Summary: A Python package to interact with DocuProx API
License: MIT License
Project-URL: Homepage, https://github.com/docuprox/docuprox-python-lib
Project-URL: Repository, https://github.com/docuprox/docuprox-python-lib
Project-URL: Issues, https://github.com/docuprox/docuprox-python-lib/issues
Classifier: Development Status :: 3 - Alpha
Classifier: Intended Audience :: Developers
Classifier: License :: OSI Approved :: MIT License
Classifier: Operating System :: OS Independent
Classifier: Programming Language :: Python :: 3
Classifier: Programming Language :: Python :: 3.6
Classifier: Programming Language :: Python :: 3.7
Classifier: Programming Language :: Python :: 3.8
Classifier: Programming Language :: Python :: 3.9
Requires-Python: >=3.6
License-File: LICENSE
Requires-Dist: requests>=2.25.0
Dynamic: license-file
